odoo/addons/website_menu_by_user_status/README.rst
odoo/addons/website_menu_by_user_status/__init__.py
odoo/addons/website_menu_by_user_status/__manifest__.py
odoo/addons/website_menu_by_user_status/i18n/ca.po
odoo/addons/website_menu_by_user_status/i18n/es.po
odoo/addons/website_menu_by_user_status/i18n/es_AR.po
odoo/addons/website_menu_by_user_status/i18n/it.po
odoo/addons/website_menu_by_user_status/i18n/website_menu_by_user_status.pot
odoo/addons/website_menu_by_user_status/models/__init__.py
odoo/addons/website_menu_by_user_status/models/website_menu.py
odoo/addons/website_menu_by_user_status/readme/CONTRIBUTORS.rst
odoo/addons/website_menu_by_user_status/readme/DESCRIPTION.rst
odoo/addons/website_menu_by_user_status/readme/ROADMAP.rst
odoo/addons/website_menu_by_user_status/readme/USAGE.rst
odoo/addons/website_menu_by_user_status/static/description/icon.png
odoo/addons/website_menu_by_user_status/static/description/index.html
odoo/addons/website_menu_by_user_status/tests/__init__.py
odoo/addons/website_menu_by_user_status/tests/test_website_menu.py
odoo/addons/website_menu_by_user_status/views/website_menu.xml
odoo14_addon_website_menu_by_user_status-14.0.1.0.1.dev9.dist-info/METADATA
odoo14_addon_website_menu_by_user_status-14.0.1.0.1.dev9.dist-info/WHEEL
odoo14_addon_website_menu_by_user_status-14.0.1.0.1.dev9.dist-info/top_level.txt
odoo14_addon_website_menu_by_user_status-14.0.1.0.1.dev9.dist-info/RECORD
